Metadata-Version: 2.1
Name: selective-self-attention
Version: 1.0.0
Summary: Complete PyTorch implementation of Selective Self-Attention (SSA) from NeurIPS 2024
Home-page: https://github.com/yourusername/selective-self-attention
Author: DeepCode Research Team
Author-email: research@deepcode.ai
Classifier: Development Status :: 5 - Production/Stable
Classifier: Intended Audience :: Science/Research
Classifier: License :: OSI Approved :: MIT License
Classifier: Operating System :: OS Independent
Classifier: Programming Language :: Python :: 3
Classifier: Programming Language :: Python :: 3.8
Classifier: Programming Language :: Python :: 3.9
Classifier: Programming Language :: Python :: 3.10
Classifier: Programming Language :: Python :: 3.11
Classifier: Topic :: Scientific/Engineering :: Artificial Intelligence
Requires-Python: >=3.8
License-File: LICENSE
Requires-Dist: pyyaml>=6.0
Requires-Dist: numpy>=1.22
Requires-Dist: matplotlib>=3.6
Provides-Extra: dev
Requires-Dist: pytest>=6.0; extra == "dev"
Requires-Dist: pytest-cov>=2.0; extra == "dev"
Requires-Dist: black>=22.0; extra == "dev"
Requires-Dist: isort>=5.0; extra == "dev"
Requires-Dist: flake8>=4.0; extra == "dev"
Provides-Extra: examples
Requires-Dist: jupyter>=1.0; extra == "examples"
Requires-Dist: matplotlib>=3.0; extra == "examples"
Requires-Dist: seaborn>=0.11; extra == "examples"
